seed_intersphinx_mapping/__init__.py
seed_intersphinx_mapping/__main__.py
seed_intersphinx_mapping/cache.py
seed_intersphinx_mapping/extension.py
seed_intersphinx_mapping/fallback_mapping.json
seed_intersphinx_mapping/py.typed
seed_intersphinx_mapping/requirements_parsers.py
seed_intersphinx_mapping-1.2.2.dist-info/LICENSE
seed_intersphinx_mapping-1.2.2.dist-info/METADATA
seed_intersphinx_mapping-1.2.2.dist-info/WHEEL
seed_intersphinx_mapping-1.2.2.dist-info/entry_points.txt
seed_intersphinx_mapping-1.2.2.dist-info/RECORD
