Metadata-Version: 2.1
Name: seed-intersphinx-mapping
Version: 1.2.2
Summary: Populate the Sphinx 'intersphinx_mapping' dictionary from the project's requirements.
Author-email: Dominic Davis-Foster <dominic@davis-foster.co.uk>
License: MIT
Keywords: documentation,intersphinx,sphinx
Home-page: https://github.com/sphinx-toolbox/seed_intersphinx_mapping
Project-URL: Issue Tracker, https://github.com/sphinx-toolbox/seed_intersphinx_mapping/issues
Project-URL: Source Code, https://github.com/sphinx-toolbox/seed_intersphinx_mapping
Project-URL: Documentation, https://seed-intersphinx-mapping.readthedocs.io/en/latest
Platform: Windows
Platform: macOS
Platform: Linux
Classifier: Development Status :: 5 - Production/Stable
Classifier: Framework :: Sphinx :: Extension
Classifier: Intended Audience :: Developers
Classifier: License :: OSI Approved :: MIT License
Classifier: Operating System :: OS Independent
Classifier: Programming Language :: Python
Classifier: Programming Language :: Python :: 3 :: Only
Classifier: Programming Language :: Python :: 3.6
Classifier: Programming Language :: Python :: 3.7
Classifier: Programming Language :: Python :: 3.8
Classifier: Programming Language :: Python :: 3.9
Classifier: Programming Language :: Python :: 3.10
Classifier: Programming Language :: Python :: 3.11
Classifier: Programming Language :: Python :: Implementation :: CPython
Classifier: Programming Language :: Python :: Implementation :: PyPy
Classifier: Topic :: Documentation
Classifier: Topic :: Documentation :: Sphinx
Classifier: Topic :: Software Development :: Documentation
Classifier: Typing :: Typed
Requires-Python: >=3.6
Requires-Dist: apeye>=1.0.1
Requires-Dist: dist-meta>=0.1.2
Requires-Dist: domdf-python-tools>=3.1.0
Requires-Dist: packaging>=21.0
Requires-Dist: pypi-json>=0.1.1
Requires-Dist: requests>=2.26.0
Requires-Dist: shippinglabel>=0.15.0
Requires-Dist: sphinx>=3.0.4
